setup.cfg
setup.py
arm/__init__.py
arm/authenticated_client.py
arm_python.egg-info/PKG-INFO
arm_python.egg-info/SOURCES.txt
arm_python.egg-info/dependency_links.txt
arm_python.egg-info/requires.txt
arm_python.egg-info/top_level.txt