Metadata-Version: 1.1
Name: arm-python
Version: 0.1.1
Summary: The Python client for the Exeriments Platform API
Home-page: https://gitlab.com/nikdon/arm-python
Author: Nikolay Donets
Author-email: nd.startup@gmail.com
License: MIT
Download-URL: https://gitlab.com/nikdon/arm-python/repository/0.1.0/archive.tar.gz
Keywords: client,api,wrapper
Platform: UNKNOWN
Classifier: Development Status :: 5 - Production/Stable
Classifier: Intended Audience :: Developers
Classifier: Intended Audience :: Financial and Insurance Industry
Classifier: Intended Audience :: Information Technology
Classifier: Topic :: Software Development :: Libraries :: Python Modules
Classifier: License :: OSI Approved :: MIT License
Classifier: Programming Language :: Python :: 2
Classifier: Programming Language :: Python :: 2.6
Classifier: Programming Language :: Python :: 2.7
Classifier: Programming Language :: Python :: 3
Classifier: Programming Language :: Python :: 3.3
Classifier: Programming Language :: Python :: 3.4
Classifier: Programming Language :: Python :: 3.5
Classifier: Programming Language :: Python :: 3.6
